odoo/addons/l10n_jp_summary_invoice/README.rst
odoo/addons/l10n_jp_summary_invoice/__init__.py
odoo/addons/l10n_jp_summary_invoice/__manifest__.py
odoo/addons/l10n_jp_summary_invoice/i18n/ja.po
odoo/addons/l10n_jp_summary_invoice/i18n/l10n_jp_summary_invoice.pot
odoo/addons/l10n_jp_summary_invoice/models/__init__.py
odoo/addons/l10n_jp_summary_invoice/models/account_billing.py
odoo/addons/l10n_jp_summary_invoice/models/account_move.py
odoo/addons/l10n_jp_summary_invoice/models/account_move_line.py
odoo/addons/l10n_jp_summary_invoice/models/account_tax.py
odoo/addons/l10n_jp_summary_invoice/models/account_tax_group.py
odoo/addons/l10n_jp_summary_invoice/models/res_company.py
odoo/addons/l10n_jp_summary_invoice/models/res_config_settings.py
odoo/addons/l10n_jp_summary_invoice/readme/CONFIGURE.md
odoo/addons/l10n_jp_summary_invoice/readme/CONTRIBUTORS.md
odoo/addons/l10n_jp_summary_invoice/readme/DESCRIPTION.md
odoo/addons/l10n_jp_summary_invoice/readme/USAGE.md
odoo/addons/l10n_jp_summary_invoice/reports/report_summary_invoice_templates.xml
odoo/addons/l10n_jp_summary_invoice/reports/summary_invoice_reports.xml
odoo/addons/l10n_jp_summary_invoice/static/description/icon.png
odoo/addons/l10n_jp_summary_invoice/static/description/index.html
odoo/addons/l10n_jp_summary_invoice/tests/__init__.py
odoo/addons/l10n_jp_summary_invoice/tests/test_l10n_jp_summary_invoice.py
odoo/addons/l10n_jp_summary_invoice/views/account_billing_views.xml
odoo/addons/l10n_jp_summary_invoice/views/account_move_views.xml
odoo/addons/l10n_jp_summary_invoice/views/account_tax_views.xml
odoo/addons/l10n_jp_summary_invoice/views/res_config_settings_views.xml
odoo_addon_l10n_jp_summary_invoice-18.0.1.1.0.dist-info/METADATA
odoo_addon_l10n_jp_summary_invoice-18.0.1.1.0.dist-info/WHEEL
odoo_addon_l10n_jp_summary_invoice-18.0.1.1.0.dist-info/top_level.txt
odoo_addon_l10n_jp_summary_invoice-18.0.1.1.0.dist-info/RECORD
